<annotation>
	<folder>raw</folder>
	<filename>blood_24.png</filename>
	<path>/mnt/c/Users/satya/OneDrive/Desktop/Evidencelens/data/raw/blood_24.png</path>
	<source>
		<database>Unknown</database>
	</source>
	<size>
		<width>1242</width>
		<height>1168</height>
		<depth>3</depth>
	</size>
	<segmented>0</segmented>
	<object>
		<name>blood_24.png</name>
		<pose>Unspecified</pose>
		<truncated>1</truncated>
		<difficult>0</difficult>
		<bndbox>
			<xmin>7</xmin>
			<ymin>68</ymin>
			<xmax>1242</xmax>
			<ymax>1064</ymax>
		</bndbox>
	</object>
</annotation>
